pynuctran/__init__.py
pynuctran/cram.py
pynuctran/depletion_scheme.py
pynuctran/solver.py
pynuctran/sparse.py
pynuctran-1.55.1021.dist-info/METADATA
pynuctran-1.55.1021.dist-info/WHEEL
pynuctran-1.55.1021.dist-info/top_level.txt
pynuctran-1.55.1021.dist-info/RECORD
