Metadata-Version: 2.1
Name: pynuctran
Version: 1.55.1021
Summary: Python library for nuclear transmutation simulations.
Home-page: https://github.com/rabieomar92/pynuctran
Author: M. R. Omar
Author-email: rabieomar@live.com
License: MIT
Platform: UNKNOWN
Requires-Dist: numpy
Requires-Dist: scipy
